phydra/__init__.py
phydra/models/__init__.py
phydra/models/chemostat/__init__.py
phydra/models/chemostat/_models.py
phydra/models/chemostat/fluxes.py
phydra/models/chemostat/forcings.py
phydra/models/chemostat/variables.py
phydra/models/sizebased/__init__.py
phydra/models/sizebased/_models.py
phydra/models/sizebased/fluxes/__init__.py
phydra/models/sizebased/fluxes/basic.py
phydra/models/sizebased/fluxes/grazing.py
phydra/models/sizebased/fluxes/growth.py
phydra/models/sizebased/forcings.py
phydra/models/sizebased/variables.py
phydra/models/slabocean/__init__.py
phydra/models/slabocean/_models.py
phydra/models/slabocean/fluxes/__init__.py
phydra/models/slabocean/fluxes/basic.py
phydra/models/slabocean/fluxes/grazing.py
phydra/models/slabocean/fluxes/growth.py
phydra/models/slabocean/fluxes/mixing.py
phydra/models/slabocean/forcings.py
phydra/models/slabocean/variables.py
phydra-0.0.2.dist-info/LICENSE
phydra-0.0.2.dist-info/METADATA
phydra-0.0.2.dist-info/WHEEL
phydra-0.0.2.dist-info/RECORD
