Metadata-Version: 2.1
Name: phydra
Version: 0.0.2
Summary: A library of marine ecosystem models using the XSO frammework (xarray-simlab-ode)
License: BSD 3-Clause
Author: Benjamin Post
Requires-Python: >=3.9,<4.0
Classifier: License :: Other/Proprietary License
Classifier: Programming Language :: Python :: 3
Classifier: Programming Language :: Python :: 3.9
Classifier: Programming Language :: Python :: 3.10
Classifier: Programming Language :: Python :: 3.11
